MANIFEST.in
README.rst
setup.py
docs/HISTORY.txt
docs/LICENSE.GPL
docs/LICENSE.txt
ftw/__init__.py
ftw.publisher.core.egg-info/PKG-INFO
ftw.publisher.core.egg-info/SOURCES.txt
ftw.publisher.core.egg-info/dependency_links.txt
ftw.publisher.core.egg-info/entry_points.txt
ftw.publisher.core.egg-info/namespace_packages.txt
ftw.publisher.core.egg-info/not-zip-safe
ftw.publisher.core.egg-info/requires.txt
ftw.publisher.core.egg-info/top_level.txt
ftw/publisher/__init__.py
ftw/publisher/core/__init__.py
ftw/publisher/core/belongs_to_parent.py
ftw/publisher/core/communication.py
ftw/publisher/core/configure.zcml
ftw/publisher/core/interfaces.py
ftw/publisher/core/states.py
ftw/publisher/core/testing.py
ftw/publisher/core/utils.py
ftw/publisher/core/adapters/__init__.py
ftw/publisher/core/adapters/backreferences.py
ftw/publisher/core/adapters/children.py
ftw/publisher/core/adapters/configure.zcml
ftw/publisher/core/adapters/constrain_types.py
ftw/publisher/core/adapters/custom_styles.py
ftw/publisher/core/adapters/dx_field_data.py
ftw/publisher/core/adapters/field_data.py
ftw/publisher/core/adapters/ftw_logo.py
ftw/publisher/core/adapters/ftw_servicenavigation.py
ftw/publisher/core/adapters/ftw_shop.py
ftw/publisher/core/adapters/ftw_simplelayout.py
ftw/publisher/core/adapters/geo_data.py
ftw/publisher/core/adapters/interface_data.py
ftw/publisher/core/adapters/plone_app_event.py
ftw/publisher/core/adapters/plone_form_gen_fg_field_data.py
ftw/publisher/core/adapters/portlet_data.py
ftw/publisher/core/adapters/properties_data.py
ftw/publisher/core/adapters/topic_criterias.py
ftw/publisher/core/locales/ftw.publisher.core.pot
ftw/publisher/core/locales/de/LC_MESSAGES/ftw.publisher.core.po
ftw/publisher/core/tests/__init__.py
ftw/publisher/core/tests/behaviors.py
ftw/publisher/core/tests/behaviors.zcml
ftw/publisher/core/tests/builders.py
ftw/publisher/core/tests/helpers.py
ftw/publisher/core/tests/interfaces.py
ftw/publisher/core/tests/test_belongs_to_parent.py
ftw/publisher/core/tests/test_constrain_types_adapter.py
ftw/publisher/core/tests/test_custom_style_adapter.py
ftw/publisher/core/tests/test_datagrid_with_relations.py
ftw/publisher/core/tests/test_dexterity.py
ftw/publisher/core/tests/test_ftw_servicenavigation.py
ftw/publisher/core/tests/test_ftw_shop.py
