Metadata-Version: 2.1
Name: ftw.publisher.core
Version: 2.14.5
Summary: Staging and publishing addon for Plone contents.
Home-page: https://github.com/4teamwork/ftw.publisher.core
Author: 4teamwork AG
Author-email: mailto:info@4teamwork.ch
Maintainer: Jonas Baumann
License: GPL2
Keywords: ftw publisher core
Platform: UNKNOWN
Classifier: Framework :: Plone
Classifier: Framework :: Plone :: 4.3
Classifier: Framework :: Plone :: 5.1
Classifier: Programming Language :: Python
Classifier: Topic :: Software Development :: Libraries :: Python Modules
Provides-Extra: dexterity
Provides-Extra: tests_plone4
Provides-Extra: tests
